rest_auth_toolkit/__init__.py
rest_auth_toolkit/admin.py
rest_auth_toolkit/app.py
rest_auth_toolkit/authentication.py
rest_auth_toolkit/fields.py
rest_auth_toolkit/managers.py
rest_auth_toolkit/models.py
rest_auth_toolkit/serializers.py
rest_auth_toolkit/utils.py
rest_auth_toolkit/views.py
rest_auth_toolkit/locale/fr/LC_MESSAGES/django.mo
rest_auth_toolkit/locale/fr/LC_MESSAGES/django.po
rest_auth_toolkit/templates/rest_auth_toolkit/email_confirmation.html
rest_auth_toolkit/templates/rest_auth_toolkit/email_confirmation.txt
rest_framework_auth_toolkit-0.14.dist-info/LICENSE
rest_framework_auth_toolkit-0.14.dist-info/WHEEL
rest_framework_auth_toolkit-0.14.dist-info/METADATA
rest_framework_auth_toolkit-0.14.dist-info/RECORD
