Metadata-Version: 2.1
Name: Rest_Framework_Auth_Toolkit
Version: 0.14
Summary: Simple + flexible signup and login for Django APIs
Author-email: Caravan Coop <hi@caravan.coop>
Requires-Python: >= 3.11
Classifier: Development Status :: 4 - Beta
Classifier: Intended Audience :: Developers
Classifier: Environment :: Web Environment
Classifier: License :: OSI Approved :: MIT License
Classifier: Programming Language :: Python :: 3
Classifier: Programming Language :: Python :: 3 :: Only
Classifier: Programming Language :: Python :: 3.11
Classifier: Programming Language :: Python :: 3.12
Classifier: Framework :: Django
Classifier: Framework :: Django :: 4.2
Classifier: Framework :: Django :: 5.0
Requires-Dist: django >= 4.2
Requires-Dist: facepy ; extra == "facebook"
Project-URL: Changelog, https://github.com/caravancoop/rest-framework-auth-toolkit/blob/main/CHANGELOG.md
Project-URL: Homepage, https://github.com/caravancoop/rest-framework-auth-toolkit
Provides-Extra: facebook
